README.md
setup.py
simplelogincli.egg-info/PKG-INFO
simplelogincli.egg-info/SOURCES.txt
simplelogincli.egg-info/dependency_links.txt
simplelogincli.egg-info/requires.txt
simplelogincli.egg-info/top_level.txt
slcli/main.py