Metadata-Version: 2.1
Name: simplelogincli
Version: 0.0.1
Summary: A simple CLI for SimpleLogin
Home-page: https://github.com/drk1rd/slcli
Author: drk1rd
Requires-Dist: simplelogin
